{
  "issues": [
    {
      "id": "1",
      "title": "Edited issue",
      "description": "This is the first issue",
      "status": "open",
      "sender": "red",
      "priority": "high",
      "verified": false,
      "created_at": "201"
    },
    {
      "id": "2",
      "title": "Edited issue",
      "description": "This is the second issue",
      "status": "open",
      "sender": "none",
      "priority": "high",
      "verified": false,
      "created_at": "201"
    },
    {
      "id": "3",
      "title": "Edited issue",
      "description": "This is the third issue",
      "status": "open",
      "sender": "green",
      "priority": "high",
      "verified": false,
      "created_at": "201"
    }
  ],
  "users": [
    {
      "id": "1",
      "name": "John Doe",
      "email": "JohnDoe@gmail.com",
      "password": "johndoe"
    }
  ]
}
